lexical_loro/__init__.py
lexical_loro/__version__.py
lexical_loro/cli.py
lexical_loro/client.py
lexical_loro/constants.py
lexical_loro/mcp/README.md
lexical_loro/mcp/__init__.py
lexical_loro/mcp/__main__.py
lexical_loro/mcp/server.py
lexical_loro/model/__init__.py
lexical_loro/model/document_manager.py
lexical_loro/model/lexical_converter.py
lexical_loro/model/lexical_loro.py
lexical_loro/model/node_mapper.py
lexical_loro/websocket/__init__.py
lexical_loro/websocket/__main__.py
lexical_loro/websocket/server.py
lexical_loro-0.1.0.dist-info/METADATA
lexical_loro-0.1.0.dist-info/WHEEL
lexical_loro-0.1.0.dist-info/entry_points.txt
lexical_loro-0.1.0.dist-info/licenses/LICENSE
lexical_loro-0.1.0.dist-info/RECORD
