Metadata-Version: 2.4
Name: lexical-loro
Version: 0.1.0
Dynamic: Author
Dynamic: Author-email
Dynamic: Summary
Dynamic: Keywords
Project-URL: Homepage, https://github.com/datalayer/lexical-loro
Project-URL: Documentation, https://github.com/datalayer/lexical-loro#readme
Project-URL: Repository, https://github.com/datalayer/lexical-loro.git
Project-URL: Issues, https://github.com/datalayer/lexical-loro/issues
License: MIT
License-File: LICENSE
Classifier: Development Status :: 3 - Alpha
Classifier: Intended Audience :: Developers
Classifier: License :: OSI Approved :: MIT License
Classifier: Programming Language :: Python :: 3
Classifier: Programming Language :: Python :: 3.8
Classifier: Programming Language :: Python :: 3.9
Classifier: Programming Language :: Python :: 3.10
Classifier: Programming Language :: Python :: 3.11
Classifier: Programming Language :: Python :: 3.12
Classifier: Topic :: Internet :: WWW/HTTP :: Dynamic Content
Classifier: Topic :: Software Development :: Libraries :: Python Modules
Classifier: Topic :: Text Processing :: Markup
Requires-Python: >=3.8
Requires-Dist: click>=8.0.0
Requires-Dist: loro>=1.6.0
Requires-Dist: mcp>=1.10.1
Requires-Dist: starlette>=0.27
Requires-Dist: uvicorn>=0.23.1
Requires-Dist: websockets>=12.0
Provides-Extra: dev
Requires-Dist: black>=23.0.0; extra == 'dev'
Requires-Dist: mypy>=1.0.0; extra == 'dev'
Requires-Dist: pytest-asyncio>=0.21.0; extra == 'dev'
Requires-Dist: pytest-cov>=4.0.0; extra == 'dev'
Requires-Dist: pytest>=7.0; extra == 'dev'
Requires-Dist: ruff>=0.1.0; extra == 'dev'
Provides-Extra: test
Requires-Dist: pytest-asyncio>=0.21.0; extra == 'test'
Requires-Dist: pytest-cov>=4.0.0; extra == 'test'
Requires-Dist: pytest>=7.0; extra == 'test'
